odoo/addons/stock_warehouse_flow_release/README.rst
odoo/addons/stock_warehouse_flow_release/__init__.py
odoo/addons/stock_warehouse_flow_release/__manifest__.py
odoo/addons/stock_warehouse_flow_release/i18n/it.po
odoo/addons/stock_warehouse_flow_release/i18n/stock_warehouse_flow_release.pot
odoo/addons/stock_warehouse_flow_release/migrations/16.0.1.1.0/post-migrate.py
odoo/addons/stock_warehouse_flow_release/models/__init__.py
odoo/addons/stock_warehouse_flow_release/models/stock_move.py
odoo/addons/stock_warehouse_flow_release/models/stock_route.py
odoo/addons/stock_warehouse_flow_release/readme/CONTRIBUTORS.rst
odoo/addons/stock_warehouse_flow_release/readme/DESCRIPTION.rst
odoo/addons/stock_warehouse_flow_release/static/description/icon.png
odoo/addons/stock_warehouse_flow_release/static/description/index.html
odoo/addons/stock_warehouse_flow_release/tests/__init__.py
odoo/addons/stock_warehouse_flow_release/tests/test_warehouse_flow_release.py
odoo_addon_stock_warehouse_flow_release-16.0.1.1.0.4.dist-info/METADATA
odoo_addon_stock_warehouse_flow_release-16.0.1.1.0.4.dist-info/WHEEL
odoo_addon_stock_warehouse_flow_release-16.0.1.1.0.4.dist-info/top_level.txt
odoo_addon_stock_warehouse_flow_release-16.0.1.1.0.4.dist-info/RECORD
