Metadata-Version: 2.1
Name: odoo-addon-stock_warehouse_flow_release
Version: 16.0.1.1.0.4
Summary: Warehouse flows integrated with Operation Release
Home-page: https://github.com/OCA/wms
Author: Camptocamp, BCIM, Odoo Community Association (OCA)
Author-email: support@odoo-community.org
License: AGPL-3
Classifier: Programming Language :: Python
Classifier: Framework :: Odoo
Classifier: Framework :: Odoo :: 16.0
Classifier: License :: OSI Approved :: GNU Affero General Public License v3
Classifier: Development Status :: 3 - Alpha
Requires-Python: >=3.10
Requires-Dist: odoo-addon-stock-available-to-promise-release<16.1dev,>=16.0dev
Requires-Dist: odoo-addon-stock-warehouse-flow<16.1dev,>=16.0dev
Requires-Dist: odoo<16.1dev,>=16.0a
